setup.py
ArgumentParser/__init__.py
argumentparser.egg-info/PKG-INFO
argumentparser.egg-info/SOURCES.txt
argumentparser.egg-info/dependency_links.txt
argumentparser.egg-info/top_level.txt