Metadata-Version: 1.1
Name: argumentparser
Version: 1.2.1
Summary: Python 2/3 compatible commandline argument parser
Home-page: UNKNOWN
Author: Tim Savannah
Author-email: kata198@gmail.com
License: LGPLv3
Keywords: argument parser,argumentparser,argument,parser,argv,sys.argv,commandline,cmd,args
Platform: UNKNOWN
Classifier: Development Status :: 5 - Production/Stable
Classifier: Programming Language :: Python
Classifier: License :: OSI Approved :: GNU Lesser General Public License v3 (LGPLv3)
Classifier: Programming Language :: Python :: 2
Classifier: Programming Language :: Python :: 2
Classifier: Programming Language :: Python :: 2.6
Classifier: Programming Language :: Python :: 2.7
Classifier: Programming Language :: Python :: 3
Classifier: Programming Language :: Python :: 3.4
Classifier: Topic :: Software Development :: Libraries :: Python Modules
